{
  "case_id": "Clinical_case_111",
  "age": "38",
  "gender_identity": "Man",
  "summary": "(RAG Format)\nThe patient presents with difficulties in managing emotional expression within his relationship. He identifies as having a more rational and solution-focused communication style, which conflicts with his partner's need for emotional validation and gentle reassurance. This has led to recurrent conflicts, particularly around misunderstandings regarding his perceived lack of empathy or emotional responsiveness. He acknowledges a tendency to shut down emotionally, a coping mechanism developed in childhood, and recognizes the need to explore and adjust his communication patterns.",
  "main_issues": [
    "- Difficulty expressing emotions and providing emotional support",
    "- Conflicts arising from rational vs. emotional communication styles",
    "- Struggles with emotional validation and showing physical affection",
    "- Tendency to dismiss emotional concerns as minor or unimportant",
    "- Feelings of frustration and misunderstanding in the relationship"
  ],
  "emotions": [
    "Frustration",
    "Confusion",
    "Guilt",
    "Defensiveness",
    "Emotional Withdrawal"
  ],
  "limiting_beliefs": [
    "- I am not capable of providing emotional support.",
    "- My partner is too sensitive; I can't meet her needs.",
    "- If I don't offer solutions, I am not being helpful.",
    "- Showing emotions is a sign of weakness."
  ],
  "therapeutic_goals": [
    "- Develop skills for emotional validation and active listening",
    "- Reframe limiting beliefs around emotional expression and vulnerability",
    "- Implement communication techniques that balance problem-solving and emotional support",
    "- Identify and release childhood conditioning around emotional suppression",
    "- Create a structured plan for conflict resolution within the relationship"
  ],
  "solutions": {
    "immediate": [
      "- Breathing exercises to reduce emotional reactivity during conflicts",
      "- Affirmations: 'I can validate my partner's feelings without offering a solution.'",
      "- Reflective listening practice: 'I hear you saying...'",
      "- Guided visualization for self-soothing and emotional grounding"
    ],
    "intermediate": [
      "- Communication skills training focused on emotional validation and empathy",
      "- Assertiveness practice to express personal boundaries without defensiveness",
      "- Self-reflection journaling to identify patterns of emotional shutdown",
      "- Hypnosis session: Reframing vulnerability as a strength, not a weakness"
    ],
    "long_term": [
      "- Monthly follow-ups to reinforce new communication patterns",
      "- Couples therapy to align communication styles and emotional needs",
      "- Integration therapy to deepen self-awareness and self-compassion",
      "- Hypnosis session: Reconnecting with emotional expression as a source of connection"
    ]
  },
  "motivational_closure": "You are capable of growing and adapting. Emotional expression is not a weakness; it is a bridge to deeper connection. You can learn to balance logic and emotion, creating a space where both you and your partner feel heard and valued.",
  "tags": [
    "EmotionalExpression",
    "CommunicationSkills",
    "EmpathyDevelopment",
    "Vulnerability",
    "RelationshipConflicts",
    "EmotionalValidation",
    "SelfAwareness",
    "ConflictResolution"
  ]
}